setup.py
c4/__init__.py
c4_framework.egg-info/PKG-INFO
c4_framework.egg-info/SOURCES.txt
c4_framework.egg-info/dependency_links.txt
c4_framework.egg-info/top_level.txt