Metadata-Version: 1.1
Name: c4-framework
Version: 0.0.1
Summary: C4 - Test automation framework
Home-page: UNKNOWN
Author: QA Automation
Author-email: UNKNOWN
License: UNKNOWN
Platform: UNKNOWN
Classifier: Programming Language :: Python :: 3
